reddit_2_album/__init__.py
reddit_2_album-0.0.10.dist-info/LICENSE
reddit_2_album-0.0.10.dist-info/METADATA
reddit_2_album-0.0.10.dist-info/WHEEL
reddit_2_album-0.0.10.dist-info/top_level.txt
reddit_2_album-0.0.10.dist-info/RECORD
