Metadata-Version: 2.1
Name: reddit-2-album
Version: 0.0.10
Summary: Return photo list and caption (markdown format) from reddit.
Home-page: https://github.com/gaoyunzhi/reddit_2_album
Author: Yunzhi Gao
Author-email: gaoyunzhi@gmail.com
License: UNKNOWN
Platform: UNKNOWN
Classifier: Programming Language :: Python :: 3
Classifier: License :: OSI Approved :: MIT License
Classifier: Operating System :: OS Independent
Requires-Python: >=3.0
Requires-Dist: bs4
Requires-Dist: telegram-util
Requires-Dist: pyyaml
Requires-Dist: praw
Requires-Dist: cached-url
Requires-Dist: Pillow
